<annotation>
  <folder>images</folder>
  <filename>img_3</filename>
  <path>D:\Tezan\Acads\Sem7\IITB_Courses\ME781\Project\McDefect\dataset_pump_impeller\object_detection\images\img_3.jpg</path>
  <source>
    <database>Unknown</database>
  </source>
  <size>
    <width>900</width>
    <height>900</height>
    <depth>1</depth>
  </size>
  <segmented>0</segmented>
  <object>
    <name>pump_impeller</name>
    <pose>Unspecified</pose>
    <truncated>0</truncated>
    <difficult>0</difficult>
    <bndbox>
      <xmin>4</xmin>
      <ymin>1</ymin>
      <xmax>292</xmax>
      <ymax>240</ymax>
    </bndbox>
  </object>
  <object>
    <name>pump_impeller</name>
    <pose>Unspecified</pose>
    <truncated>0</truncated>
    <difficult>0</difficult>
    <bndbox>
      <xmin>302</xmin>
      <ymin>70</ymin>
      <xmax>581</xmax>
      <ymax>345</ymax>
    </bndbox>
  </object>
  <object>
    <name>pump_impeller</name>
    <pose>Unspecified</pose>
    <truncated>0</truncated>
    <difficult>0</difficult>
    <bndbox>
      <xmin>607</xmin>
      <ymin>12</ymin>
      <xmax>891</xmax>
      <ymax>299</ymax>
    </bndbox>
  </object>
  <object>
    <name>pump_impeller</name>
    <pose>Unspecified</pose>
    <truncated>0</truncated>
    <difficult>0</difficult>
    <bndbox>
      <xmin>1</xmin>
      <ymin>275</ymin>
      <xmax>288</xmax>
      <ymax>554</ymax>
    </bndbox>
  </object>
  <object>
    <name>pump_impeller</name>
    <pose>Unspecified</pose>
    <truncated>0</truncated>
    <difficult>0</difficult>
    <bndbox>
      <xmin>320</xmin>
      <ymin>366</ymin>
      <xmax>603</xmax>
      <ymax>638</ymax>
    </bndbox>
  </object>
  <object>
    <name>pump_impeller</name>
    <pose>Unspecified</pose>
    <truncated>0</truncated>
    <difficult>0</difficult>
    <bndbox>
      <xmin>621</xmin>
      <ymin>308</ymin>
      <xmax>890</xmax>
      <ymax>588</ymax>
    </bndbox>
  </object>
  <object>
    <name>pump_impeller</name>
    <pose>Unspecified</pose>
    <truncated>0</truncated>
    <difficult>0</difficult>
    <bndbox>
      <xmin>21</xmin>
      <ymin>586</ymin>
      <xmax>288</xmax>
      <ymax>854</ymax>
    </bndbox>
  </object>
  <object>
    <name>pump_impeller</name>
    <pose>Unspecified</pose>
    <truncated>0</truncated>
    <difficult>0</difficult>
    <bndbox>
      <xmin>299</xmin>
      <ymin>656</ymin>
      <xmax>597</xmax>
      <ymax>900</ymax>
    </bndbox>
  </object>
  <object>
    <name>pump_impeller</name>
    <pose>Unspecified</pose>
    <truncated>0</truncated>
    <difficult>0</difficult>
    <bndbox>
      <xmin>622</xmin>
      <ymin>616</ymin>
      <xmax>884</xmax>
      <ymax>875</ymax>
    </bndbox>
  </object>
</annotation>
